{
  "MOD.LOADED": "无障碍模组已加载。",
  "TYPES.BUTTON": "按钮",
  "TYPES.CHECKBOX": "复选框",
  "TYPES.SLIDER": "滑块",
  "TYPES.DROPDOWN": "下拉菜单",
  "TYPES.CARD": "卡牌",
  "TYPES.RELIC": "遗物",
  "TYPES.POTION": "药水",
  "TYPES.ORB": "充能球",
  "TYPES.MAP NODE": "地图节点",
  "TYPES.SHOP ITEM": "商店物品",
  "TYPES.CREATURE": "生物",
  "TYPES.KEYBIND": "按键绑定",
  "TYPES.ATTACK": "攻击",
  "TYPES.SKILL": "技能",
  "TYPES.POWER": "能力",
  "TYPES.STATUS": "状态",
  "TYPES.CURSE": "诅咒",
  "TYPES.QUEST": "任务",
  "KEYBIND.LISTENING": "按下一个按键以重新绑定 {action}",
  "KEYBIND.BOUND": "{action} 已绑定至 {key}",
  "KEYBIND.SWAPPED": "{action} 已改绑为 {key}",
  "KEYBIND.RESET": "按键绑定已重置为默认设置",
  "KEYBINDINGS.CATEGORY": "Keybindings",
  "KEYBINDINGS.CATEGORIES.BUFFERS": "Buffers",
  "KEYBINDINGS.CATEGORIES.COMBAT": "Combat",
  "KEYBINDINGS.CATEGORIES.COMBATANT_INTENT": "Combatant Intent",
  "KEYBINDINGS.CATEGORIES.COMBATANT_STATUS": "Combatant Status",
  "KEYBINDINGS.CATEGORIES.GENERAL": "General",
  "KEYBINDINGS.CATEGORIES.MAP": "Map",
  "KEYBINDINGS.CATEGORIES.MARKERS": "Markers",
  "KEYBINDINGS.CATEGORIES.MOD": "Mod",
  "KEYBINDINGS.CATEGORIES.NAVIGATION": "Navigation",
  "KEYBINDINGS.CATEGORIES.RUN_INFORMATION": "Run Information",
  "EVENT.MAP_VOTE_LOCAL": "Voted for {node}",
  "EVENT.MAP_VOTE_SKIP": "{player} skipped",
  "EVENT.MAP_VOTE_SKIP_LOCAL": "Skipped",
  "EVENT.MAP_TRAVEL": "Traveling to {node}",
  "EVENT.VOTED_FOR_BY": "voted for by {players}",
  "BUFFERS.UI": "界面",
  "BUFFERS.CHARACTER": "角色",
  "BUFFERS.CARD": "卡牌",
  "BUFFERS.CREATURE": "生物",
  "BUFFERS.PLAYER": "玩家",
  "BUFFERS.MONSTER": "怪物",
  "BUFFERS.RELIC": "遗物",
  "BUFFERS.POTION": "药水",
  "BUFFERS.ORB": "充能球",
  "BUFFERS.NO_BUFFERS": "没有可用缓冲区",
  "BUFFERS.NO_BUFFER_SELECTED": "未选择缓冲区",
  "BUFFERS.EMPTY": "{buffer}: 空",
  "BUFFERS.CURRENT": "{buffer}: {item}",
  "CHECKBOX.CHECKED": "已勾选",
  "CHECKBOX.UNCHECKED": "未勾选",
  "POSITIONS.LIST": "{position} / {total}",
  "POSITIONS.GRID": "第 {row} 行, 第 {column} 列",
  "POSITIONS.CATEGORY_LIST": "{position} / {total} {category}",
  "CUSTOM_RUN.START": "Start custom run",
  "CUSTOM_RUN.ROWS.SEED": "Seed",
  "CUSTOM_RUN.ROWS.CHARACTERS": "Characters",
  "CUSTOM_RUN.ROWS.ASCENSION": "Ascension",
  "CUSTOM_RUN.ROWS.MODIFIERS": "Modifiers",
  "CARD_LIBRARY.SCREEN_NAME": "Card Library",
  "CARD_LIBRARY.SEARCH": "Search",
  "CARD_LIBRARY.CARDS": "Cards",
  "CARD_LIBRARY.ROWS.POOLS": "Pools",
  "CARD_LIBRARY.ROWS.SORT": "Sort",
  "CARD_LIBRARY.ROWS.TYPE": "Type",
  "CARD_LIBRARY.ROWS.RARITY": "Rarity",
  "CARD_LIBRARY.ROWS.COST": "Cost",
  "CARD_LIBRARY.ROWS.DISPLAY": "Display",
  "CARD.UPGRADE_UNAVAILABLE": "无可用升级",
  "DAILY_RUN_LEADERBOARD.FLOOR": "Floor {floor}",
  "DAILY_RUN_LEADERBOARD.BADGES": "Badges {badges}",
  "DAILY_RUN_LEADERBOARD.TIME": "Time {time}"
}
